{
    "enabled": true,
    "neededInstalledMods": [],
    "neededUninstalledMods": [],
    "spawns": [
        {
            "id": "togedemaru-1",
            "pokemon": "togedemaru",
            "presets": [
                "natural",
                "wild"
            ],
            "type": "pokemon",
            "context": "grounded",
            "bucket": "uncommon",
            "level": "22-45",
            "weight": 8.0,
            "condition": {
                "biomes": [
                    "#cobblemon:is_highlands"              
                ]
            }
        }
    ]
}